runnerase/__init__.py
runnerase/calculator.py
runnerase/defaultoptions.py
runnerase/singlepoint.py
runnerase/storageclasses.py
runnerase/symmetryfunctions.py
runnerase/utils.py
runnerase/io/__init__.py
runnerase/io/ase.py
runnerase/io/runnerconfig.py
runnerase/io/storageclasses.py
runnerase/io/structuredata.py
runnerase/plot/__init__.py
runnerase/plot/calculator.py
runnerase/plot/fitresults.py
runnerase/plot/scaling.py
runnerase/plot/setup.py
runnerase/plot/sfvalues.py
runnerase/plot/splittraintest.py
runnerase/plot/symmetryfunctions.py
runnerase/plot/weights.py
runnerase/plot/mpl_styles/__init__.py
runnerase/plot/mpl_styles/bar.mplstyle
runnerase/plot/mpl_styles/hist.mplstyle
runnerase/plot/mpl_styles/line.mplstyle
runnerase/plot/mpl_styles/paper.mplstyle
runnerase/plot/mpl_styles/presentation.mplstyle
runnerase/plot/mpl_styles/scatterplot.mplstyle
runnerase-0.3.3.dist-info/LICENSE
runnerase-0.3.3.dist-info/METADATA
runnerase-0.3.3.dist-info/WHEEL
runnerase-0.3.3.dist-info/top_level.txt
runnerase-0.3.3.dist-info/RECORD
