Metadata-Version: 2.1
Name: runnerase
Version: 0.3.3
Summary: An Interface between the Runner Neural Network Energy Representation (RuNNer) and the Atomic Simulation Environment (ASE).
Author-email: Alexander Knoll <alexknoll@mailbox.org>
Maintainer-email: Alexander Knoll <alexknoll@mailbox.org>
License: GPLv3+
Project-URL: Source, https://gitlab.com/runner-suite/runnerase
Project-URL: Bugs, https://gitlab.com/runner-suite/runnerase/issues
Project-URL: Documentation, https://runner-suite.gitlab.com/runnerase
Keywords: computational chemistry,machine learning,atomic simulation environment
Classifier: Topic :: Scientific/Engineering :: Chemistry
Classifier: Intended Audience :: Science/Research
Classifier: Development Status :: 4 - Beta
Classifier: Operating System :: OS Independent
Classifier: Programming Language :: Python :: 3
Classifier: License :: OSI Approved :: GNU General Public License v3 or later (GPLv3+)
Classifier: Typing :: Typed
Requires-Python: >=3.6
License-File: LICENSE
Requires-Dist: numpy (>=1.17.0)
Requires-Dist: ase (>=3.19.0)
Requires-Dist: scikit-learn (>=1.2.0)
Provides-Extra: deploy
Requires-Dist: mkdocs (>=1.3.0) ; extra == 'deploy'
Requires-Dist: mkdocs-material (>=8.2.0) ; extra == 'deploy'
Requires-Dist: mkdocstrings[python-legacy] (>=0.18.0) ; extra == 'deploy'
Requires-Dist: mike (>=1.1.0) ; extra == 'deploy'
Requires-Dist: build (>=0.7.0) ; extra == 'deploy'
Requires-Dist: twine (>=4.0.0) ; extra == 'deploy'
Requires-Dist: pytkdocs[numpy-style] (>=0.16.0) ; extra == 'deploy'
Provides-Extra: test
Requires-Dist: mypy (>=0.942) ; extra == 'test'
Requires-Dist: flake8 (>=4.0.0) ; extra == 'test'
Requires-Dist: pylint (>=2.13.0) ; extra == 'test'
Requires-Dist: pydocstyle (>=6.0.0) ; extra == 'test'
Requires-Dist: pytest (>=7.1.0) ; extra == 'test'
Requires-Dist: pytest-cov (>=3.0.0) ; extra == 'test'
